README.md
setup.cfg
setup.py
nannypi.egg-info/PKG-INFO
nannypi.egg-info/SOURCES.txt
nannypi.egg-info/dependency_links.txt
nannypi.egg-info/requires.txt
nannypi.egg-info/top_level.txt
src/send_telegram_media.py