Metadata-Version: 2.1
Name: nannypi
Version: 0.1.1
Summary: Collection of python scripts used to automate a raspberry pi and telegram powered nanny cam.
Home-page: https://gitlab.com/rveach/nannypi
Author: Ryan Veach
Author-email: rveach@gmail.com
License: MIT
Keywords: Nanny,Telegram
Platform: UNKNOWN
Classifier: Development Status :: 4 - Beta
Classifier: Intended Audience :: Developers
Classifier: License :: OSI Approved :: MIT License
Classifier: Topic :: Software Development :: Libraries :: Python Modules
Classifier: Topic :: Internet
Classifier: Programming Language :: Python :: 3
Classifier: Programming Language :: Python :: 3.6
Classifier: Programming Language :: Python :: 3.7
Requires-Python: >=3
